cotter/__init__.py
cotter/constants.py
cotter/errors.py
cotter/tokenhandler.py
cotter/validate.py
cotter-0.0.7.dist-info/LICENSE
cotter-0.0.7.dist-info/METADATA
cotter-0.0.7.dist-info/WHEEL
cotter-0.0.7.dist-info/top_level.txt
cotter-0.0.7.dist-info/RECORD
