Metadata-Version: 2.1
Name: cotter
Version: 0.0.7
Summary: Cotter Login SDK for python scripts
Home-page: https://github.com/cotterapp/python-sdk
Author: Cotter
Author-email: putri@cotter.app
License: UNKNOWN
Platform: UNKNOWN
Classifier: Programming Language :: Python :: 3
Classifier: License :: OSI Approved :: MIT License
Classifier: Operating System :: OS Independent
Requires-Dist: requests
Requires-Dist: python-jose
Requires-Dist: cryptography
